RiZoeLX/__init__.py
RiZoeLX/developers.py
RiZoeLX/version.py
RiZoeLX/data/__init__.py
RiZoeLX/data/spamx.py
RiZoeLX/data/tags.py
RiZoeLX/data/usage_data.py
RiZoeLX/data/vars.py
RiZoeLX/docs/__init__.py
RiZoeLX/functions/__init__.py
RiZoeLX/functions/admins.py
RiZoeLX/functions/broadcast.py
RiZoeLX/functions/custom_filters.py
RiZoeLX/functions/get_info.py
RiZoeLX/functions/get_time.py
RiZoeLX/functions/get_user.py
RiZoeLX/functions/list.py
RiZoeLX/functions/purges.py
RiZoeLX/functions/scraper.py
RiZoeLX/functions/spamx.py
RiZoeLX/functions/voicechat.py
RiZoeLX/functions/watchers.py
RiZoeLX/functions/welcome_message.py
twatcher/__init__.py
pyRiZoeLX-1.1.4.dist-info/LICENSE
pyRiZoeLX-1.1.4.dist-info/METADATA
pyRiZoeLX-1.1.4.dist-info/WHEEL
pyRiZoeLX-1.1.4.dist-info/top_level.txt
pyRiZoeLX-1.1.4.dist-info/RECORD
