Metadata-Version: 2.1
Name: pyRiZoeLX
Version: 1.1.4
Summary: A Pyrogram based functional module.
Home-page: https://github.com/RiZoeLX/pyRiZoeLX
Author: MrRiZoeL
Author-email: xrizoel@gmail.com
License: GNU General Public License v3.0
Keywords: telegram,pyRiZoeLX,RiZoeLX,pyrogram,functions,py-RiZoeLX
Platform: UNKNOWN
Classifier: Framework :: AsyncIO
Classifier: Development Status :: 3 - Alpha
Classifier: Intended Audience :: Developers
Classifier: License :: OSI Approved :: GNU General Public License v2 or later (GPLv2+)
Classifier: Natural Language :: English
Classifier: Operating System :: OS Independent
Classifier: Programming Language :: Python :: 3.7
Classifier: Programming Language :: Python :: 3.8
Classifier: Programming Language :: Python :: 3.9
Classifier: Programming Language :: Python :: 3.10
Classifier: Topic :: Internet :: WWW/HTTP
Classifier: Topic :: Software Development :: Libraries
Classifier: Topic :: Software Development :: Build Tools
License-File: LICENSE
Requires-Dist: PhoenixScanner
Requires-Dist: pyrogram
Requires-Dist: telethon
